alexachatbot/__init__.py
alexachatbot/alexaAI.py
alexachatbot-0.0.2.dist-info/LICENSE
alexachatbot-0.0.2.dist-info/METADATA
alexachatbot-0.0.2.dist-info/WHEEL
alexachatbot-0.0.2.dist-info/top_level.txt
alexachatbot-0.0.2.dist-info/RECORD
