Metadata-Version: 2.1
Name: alexachatbot
Version: 0.0.2
Summary: UNKNOWN
Home-page: https://github.com/A-l-t-e-r-o/Alexa-chatbot
Author: Karan Prasad
Author-email: alteromiiller@gmail.com
License: MIT
Keywords: chatbot,alexa chatbot,chatbot api,alexa api
Platform: UNKNOWN
Requires-Python: >=3.8
Requires-Dist: urllib3 (>=1.25)
Provides-Extra: dev
Requires-Dist: pytest (>=6.2.3) ; extra == 'dev'
